m4s2mp3/__init__.py
m4s2mp3/cli.py
m4s2mp3/converter.py
m4s2mp3-0.1.3.dist-info/entry_points.txt
m4s2mp3-0.1.3.dist-info/LICENSE
m4s2mp3-0.1.3.dist-info/METADATA
m4s2mp3-0.1.3.dist-info/WHEEL
m4s2mp3-0.1.3.dist-info/RECORD
