Metadata-Version: 2.3
Name: m4s2mp3
Version: 0.1.3
Summary: A Python package for converting M4S audio files to MP3 format.
Author: floyda
Author-email: floyda@163.com
Requires-Python: >=3.9
Classifier: Programming Language :: Python :: 3
Classifier: Programming Language :: Python :: 3.9
Classifier: Programming Language :: Python :: 3.10
Classifier: Programming Language :: Python :: 3.11
Classifier: Programming Language :: Python :: 3.12
Classifier: Programming Language :: Python :: 3.13
Requires-Dist: pydub (>=0.25.1,<0.26.0)
Project-URL: Bug Tracker, https://gitee.com/floyda/m4s2mp3/issues
Project-URL: Homepage, https://gitee.com/floyda/m4s2mp3
